solax_py_library/__init__.py
solax_py_library/device/__init__.py
solax_py_library/device/constant/__init__.py
solax_py_library/device/constant/cabinet.py
solax_py_library/device/constant/inverter_model_info.py
solax_py_library/device/core/__init__.py
solax_py_library/device/core/interver/__init__.py
solax_py_library/device/core/interver/base.py
solax_py_library/device/types/__init__.py
solax_py_library/device/types/alarm.py
solax_py_library/device/types/device.py
solax_py_library/device/types/inverter_config.py
solax_py_library/device/types/modbus_point.py
solax_py_library/exception.py
solax_py_library/smart_scene/__init__.py
solax_py_library/smart_scene/constant/__init__.py
solax_py_library/smart_scene/constant/message_entry.py
solax_py_library/smart_scene/core/__init__.py
solax_py_library/smart_scene/core/action/__init__.py
solax_py_library/smart_scene/core/action/base.py
solax_py_library/smart_scene/core/action/ems_action.py
solax_py_library/smart_scene/core/action/system_action.py
solax_py_library/smart_scene/core/condition/__init__.py
solax_py_library/smart_scene/core/condition/base.py
solax_py_library/smart_scene/core/condition/cabinet_condition.py
solax_py_library/smart_scene/core/condition/date_condition.py
solax_py_library/smart_scene/core/condition/price_condition.py
solax_py_library/smart_scene/core/condition/system_condition.py
solax_py_library/smart_scene/core/condition/weather_condition.py
solax_py_library/smart_scene/core/service/__init__.py
solax_py_library/smart_scene/core/service/check.py
solax_py_library/smart_scene/core/service/runner.py
solax_py_library/smart_scene/exceptions/__init__.py
solax_py_library/smart_scene/exceptions/price.py
solax_py_library/smart_scene/exceptions/smart_scene.py
solax_py_library/smart_scene/exceptions/weather.py
solax_py_library/smart_scene/types/__init__.py
solax_py_library/smart_scene/types/action.py
solax_py_library/smart_scene/types/condition.py
solax_py_library/smart_scene/types/condition_value.py
solax_py_library-1.0.0.2901.dist-info/METADATA
solax_py_library-1.0.0.2901.dist-info/WHEEL
solax_py_library-1.0.0.2901.dist-info/RECORD
