Metadata-Version: 2.1
Name: solax-py-library
Version: 1.0.0.2901
Summary: some common tool
Author: shenlvyu
Author-email: 13296718439@163.com
Requires-Python: >=3.8,<4.0
Classifier: Programming Language :: Python :: 3
Classifier: Programming Language :: Python :: 3.8
Classifier: Programming Language :: Python :: 3.9
Classifier: Programming Language :: Python :: 3.10
Classifier: Programming Language :: Python :: 3.11
Classifier: Programming Language :: Python :: 3.12
Classifier: Programming Language :: Python :: 3.13
Requires-Dist: pydantic (>=1.10.0,<2.0.0)
Requires-Dist: requests (==2.32.3)
Requires-Dist: typing-extensions (==4.7.1)
